zeta/__init__.py
zeta/colormap/__init__.py
zeta/colormap/cmap.py
zeta/colormap/palette.py
zeta/colormap/rcmod.py
zeta/plot/__init__.py
zeta/plot/categorical.py
zeta/plot/continuos.py
zeta/plot/scalers.py
zeta/plot/utils.py
zeta/typing/generics.py
libzeta-0.1.0.dist-info/METADATA
libzeta-0.1.0.dist-info/WHEEL
libzeta-0.1.0.dist-info/RECORD
